Metadata-Version: 2.4
Name: appiumfw
Version: 0.1.4
Summary: Appiumfw - A minimal appium test framework that adapt POM
Author-email: Muhamad Badru Salam <badrusalam760@gmail.com>
License: MIT
Requires-Python: >=3.8
License-File: LICENSE
Requires-Dist: typer[all]
Requires-Dist: flask
Requires-Dist: pyyaml
Requires-Dist: apscheduler
Requires-Dist: jinja2
Requires-Dist: requests
Requires-Dist: python-dotenv
Requires-Dist: Appium-Python-Client
Requires-Dist: behave
Requires-Dist: reportlab
Requires-Dist: InquirerPy
Dynamic: license-file
